cle/__init__.py
cle/address_translator.py
cle/errors.py
cle/gdb.py
cle/loader.py
cle/memory.py
cle/patched_stream.py
cle/py.typed
cle/utils.py
cle/backends/__init__.py
cle/backends/backend.py
cle/backends/binja.py
cle/backends/blob.py
cle/backends/cartfile.py
cle/backends/coff.py
cle/backends/ihex.py
cle/backends/inlined_function.py
cle/backends/named_region.py
cle/backends/region.py
cle/backends/regions.py
cle/backends/relocation.py
cle/backends/srec.py
cle/backends/static_archive.py
cle/backends/symbol.py
cle/backends/te.py
cle/backends/uefi_firmware.py
cle/backends/xbe.py
cle/backends/cgc/__init__.py
cle/backends/cgc/backedcgc.py
cle/backends/cgc/cgc.py
cle/backends/elf/__init__.py
cle/backends/elf/compilation_unit.py
cle/backends/elf/elf.py
cle/backends/elf/elfcore.py
cle/backends/elf/hashtable.py
cle/backends/elf/lsda.py
cle/backends/elf/metaelf.py
cle/backends/elf/regions.py
cle/backends/elf/subprogram.py
cle/backends/elf/symbol.py
cle/backends/elf/symbol_type.py
cle/backends/elf/variable.py
cle/backends/elf/variable_type.py
cle/backends/elf/relocation/__init__.py
cle/backends/elf/relocation/amd64.py
cle/backends/elf/relocation/arm.py
cle/backends/elf/relocation/arm64.py
cle/backends/elf/relocation/elfreloc.py
cle/backends/elf/relocation/generic.py
cle/backends/elf/relocation/i386.py
cle/backends/elf/relocation/mips.py
cle/backends/elf/relocation/ppc.py
cle/backends/elf/relocation/ppc64.py
cle/backends/elf/relocation/s390x.py
cle/backends/elf/relocation/sparc.py
cle/backends/externs/__init__.py
cle/backends/externs/simdata/__init__.py
cle/backends/externs/simdata/common.py
cle/backends/externs/simdata/glibc_startup.py
cle/backends/externs/simdata/io_file.py
cle/backends/externs/simdata/simdata.py
cle/backends/java/__init__.py
cle/backends/java/android_lifecycle.py
cle/backends/java/apk.py
cle/backends/java/jar.py
cle/backends/java/soot.py
cle/backends/macho/__init__.py
cle/backends/macho/binding.py
cle/backends/macho/encrypted_sentinel_backer.py
cle-9.2.193.dist-info/licenses/LICENSE
cle-9.2.193.dist-info/METADATA
cle-9.2.193.dist-info/WHEEL
cle-9.2.193.dist-info/top_level.txt
cle-9.2.193.dist-info/RECORD
