Metadata-Version: 2.4
Name: cle
Version: 9.2.193
Summary: CLE Loads Everything (at least, many binary formats!) and provides a pythonic interface to analyze what they are and what they would look like in memory.
License-Expression: BSD-2-Clause
Project-URL: Homepage, https://api.angr.io/projects/cle/en/latest/
Project-URL: Repository, https://github.com/angr/cle
Classifier: Programming Language :: Python :: 3
Classifier: Programming Language :: Python :: 3 :: Only
Classifier: Programming Language :: Python :: 3.10
Classifier: Programming Language :: Python :: 3.11
Classifier: Programming Language :: Python :: 3.12
Classifier: Programming Language :: Python :: 3.13
Requires-Python: >=3.10
License-File: LICENSE
Requires-Dist: archinfo==9.2.193
Requires-Dist: arpy==1.1.1
Requires-Dist: cart
Requires-Dist: minidump>=0.0.10
Requires-Dist: pefile
Requires-Dist: pyelftools>=0.29
Requires-Dist: pyvex==9.2.193
Requires-Dist: pyxbe~=1.0.3
Requires-Dist: pyxdia~=0.1
Requires-Dist: sortedcontainers>=2.0
Requires-Dist: uefi-firmware>=1.10
Provides-Extra: docs
Requires-Dist: furo; extra == "docs"
Requires-Dist: myst-parser; extra == "docs"
Requires-Dist: sphinx; extra == "docs"
Requires-Dist: sphinx-autodoc-typehints; extra == "docs"
Provides-Extra: pcode
Requires-Dist: pypcode>=1.1; extra == "pcode"
Provides-Extra: testing
Requires-Dist: cffi; extra == "testing"
Requires-Dist: pypcode>=1.1; extra == "testing"
Requires-Dist: pytest; extra == "testing"
Requires-Dist: pytest-xdist; extra == "testing"
Requires-Dist: types-pefile; extra == "testing"
Dynamic: license-file
